{
  "universe": "XETRA",
  "n_periods": 103,
  "years": 25.8,
  "frequency": "quarterly",
  "cash_periods": 0,
  "invested_periods": 103,
  "avg_stocks_when_invested": 20.8,
  "portfolio": {
    "total_return": 984.6,
    "cagr": 9.7,
    "max_drawdown": -51.85,
    "annualized_volatility": 20.93,
    "sharpe_ratio": 0.368,
    "sortino_ratio": 0.583,
    "calmar_ratio": 0.187,
    "var_95": -13.19,
    "max_consecutive_losses": 7,
    "pct_negative_periods": 42.72
  },
  "spy": {
    "total_return": 261.77,
    "cagr": 5.12,
    "max_drawdown": -65.15,
    "annualized_volatility": 22.49,
    "sharpe_ratio": 0.139,
    "sortino_ratio": 0.198,
    "calmar_ratio": 0.079,
    "var_95": -16.61,
    "max_consecutive_losses": 5,
    "pct_negative_periods": 34.95
  },
  "comparison": {
    "excess_cagr": 4.58,
    "win_rate": 54.37,
    "information_ratio": 0.283,
    "tracking_error": 14.04,
    "up_capture": 87.63,
    "down_capture": 51.63,
    "beta": 0.738,
    "alpha": 5.4
  },
  "excess_cagr": 4.58,
  "win_rate_vs_spy": 54.37,
  "annual_returns": [
    {
      "year": 2000,
      "portfolio": 6.75,
      "spy": -6.83,
      "excess": 13.58
    },
    {
      "year": 2001,
      "portfolio": 5.74,
      "spy": -17.84,
      "excess": 23.58
    },
    {
      "year": 2002,
      "portfolio": -22.0,
      "spy": -39.92,
      "excess": 17.92
    },
    {
      "year": 2003,
      "portfolio": 21.07,
      "spy": 29.42,
      "excess": -8.35
    },
    {
      "year": 2004,
      "portfolio": 20.59,
      "spy": 6.79,
      "excess": 13.8
    },
    {
      "year": 2005,
      "portfolio": 20.89,
      "spy": 26.99,
      "excess": -6.1
    },
    {
      "year": 2006,
      "portfolio": 30.36,
      "spy": 22.59,
      "excess": 7.77
    },
    {
      "year": 2007,
      "portfolio": 43.62,
      "spy": 18.98,
      "excess": 24.64
    },
    {
      "year": 2008,
      "portfolio": -45.88,
      "spy": -37.44,
      "excess": -8.44
    },
    {
      "year": 2009,
      "portfolio": 40.97,
      "spy": 21.62,
      "excess": 19.34
    },
    {
      "year": 2010,
      "portfolio": 24.64,
      "spy": 15.57,
      "excess": 9.08
    },
    {
      "year": 2011,
      "portfolio": -16.59,
      "spy": -13.08,
      "excess": -3.51
    },
    {
      "year": 2012,
      "portfolio": 18.76,
      "spy": 28.03,
      "excess": -9.28
    },
    {
      "year": 2013,
      "portfolio": 20.48,
      "spy": 20.84,
      "excess": -0.36
    },
    {
      "year": 2014,
      "portfolio": 31.19,
      "spy": 3.88,
      "excess": 27.32
    },
    {
      "year": 2015,
      "portfolio": 6.98,
      "spy": 5.31,
      "excess": 1.67
    },
    {
      "year": 2016,
      "portfolio": 26.67,
      "spy": 12.79,
      "excess": 13.88
    },
    {
      "year": 2017,
      "portfolio": 13.16,
      "spy": 10.98,
      "excess": 2.18
    },
    {
      "year": 2018,
      "portfolio": -6.74,
      "spy": -17.8,
      "excess": 11.06
    },
    {
      "year": 2019,
      "portfolio": 23.19,
      "spy": 26.52,
      "excess": -3.33
    },
    {
      "year": 2020,
      "portfolio": -12.48,
      "spy": 2.55,
      "excess": -15.02
    },
    {
      "year": 2021,
      "portfolio": 31.8,
      "spy": 16.71,
      "excess": 15.09
    },
    {
      "year": 2022,
      "portfolio": -7.34,
      "spy": -12.18,
      "excess": 4.84
    },
    {
      "year": 2023,
      "portfolio": 12.31,
      "spy": 19.19,
      "excess": -6.88
    },
    {
      "year": 2024,
      "portfolio": 1.72,
      "spy": 19.41,
      "excess": -17.69
    },
    {
      "year": 2025,
      "portfolio": 16.37,
      "spy": 21.96,
      "excess": -5.59
    }
  ]
}