{
  "universe": "XETRA",
  "period": "2000-2025 (25 years)",
  "rebalancing": "annual (April 1)",
  "weighting": "equal weight",
  "transaction_costs": "0.1-0.5% per trade (size-tiered)",
  "sector_exclusions": "Financial Services",
  "ccc_thresholds": {
    "low": "< 30 days",
    "high": "> 90 days"
  },
  "portfolios": {
    "low_ccc": {
      "cagr": 7.3,
      "total_return": 482.02,
      "volatility": 21.07,
      "sharpe": 0.252,
      "sortino": 0.498,
      "calmar": 0.193,
      "max_drawdown": -37.9,
      "var_95": -29.8,
      "pct_negative_years": 32.0,
      "max_consecutive_losses": 2
    },
    "mid_ccc": {
      "cagr": 6.56,
      "total_return": 389.74,
      "volatility": 23.45,
      "sharpe": 0.195,
      "sortino": 0.415,
      "calmar": 0.168,
      "max_drawdown": -39.0,
      "var_95": -31.8,
      "pct_negative_years": 28.0,
      "max_consecutive_losses": 2
    },
    "high_ccc": {
      "cagr": 7.86,
      "total_return": 563.7,
      "volatility": 22.53,
      "sharpe": 0.26,
      "sortino": 0.551,
      "calmar": 0.219,
      "max_drawdown": -36.0,
      "var_95": -30.7,
      "pct_negative_years": 28.0,
      "max_consecutive_losses": 2
    },
    "low_decreasing": {
      "cagr": 7.78,
      "total_return": 550.82,
      "volatility": 20.22,
      "sharpe": 0.286,
      "sortino": 0.604,
      "calmar": 0.209,
      "max_drawdown": -37.2,
      "var_95": -18.5,
      "pct_negative_years": 32.0,
      "max_consecutive_losses": 2
    },
    "sp500": {
      "cagr": 4.51,
      "total_return": 201.39,
      "volatility": 26.28,
      "sharpe": 0.096,
      "sortino": 0.164,
      "calmar": 0.069,
      "max_drawdown": -65.1,
      "var_95": -35.3,
      "pct_negative_years": 44.0,
      "max_consecutive_losses": 3
    }
  },
  "spread_cagr": -0.56,
  "low_vs_spy": 2.79,
  "avg_stock_counts": {
    "low": 99.0,
    "mid": 83.0,
    "high": 88.0,
    "low_decreasing": 55.0,
    "total": 271.0
  },
  "cash_periods": {
    "low": 0,
    "high": 0,
    "low_decreasing": 0
  },
  "decade_breakdown": [
    {
      "period": "2000-04",
      "low_return": 3.8,
      "high_return": 3.2,
      "spread": 0.6,
      "spy_return": -3.7
    },
    {
      "period": "2005-09",
      "low_return": 10.6,
      "high_return": 14.0,
      "spread": -3.4,
      "spy_return": 11.8
    },
    {
      "period": "2010-14",
      "low_return": 16.9,
      "high_return": 15.4,
      "spread": 1.5,
      "spy_return": 14.2
    },
    {
      "period": "2015-19",
      "low_return": 2.6,
      "high_return": 3.5,
      "spread": -0.9,
      "spy_return": -3.2
    },
    {
      "period": "2020-25",
      "low_return": 12.7,
      "high_return": 14.4,
      "spread": -1.7,
      "spy_return": 20.3
    }
  ],
  "low_vs_spy_detail": {
    "excess_cagr": 2.79,
    "information_ratio": 0.152,
    "tracking_error": 9.39,
    "up_capture": 85.8,
    "down_capture": 47.4,
    "beta": 0.758,
    "alpha": 3.4
  },
  "low_decreasing_vs_spy": {
    "excess_cagr": 3.27,
    "information_ratio": 0.151,
    "tracking_error": 11.38,
    "up_capture": 83.4,
    "down_capture": 37.8,
    "beta": 0.702,
    "alpha": 4.02
  },
  "annual_returns": [
    {
      "year": 2000,
      "low": -3.98,
      "mid": 4.63,
      "high": -1.82,
      "low_decreasing": -1.62,
      "spy": -22.46,
      "low_count": 13,
      "mid_count": 8,
      "high_count": 14,
      "low_decreasing_count": 10
    },
    {
      "year": 2001,
      "low": 3.25,
      "mid": -5.07,
      "high": 0.18,
      "low_decreasing": 9.24,
      "spy": -7.81,
      "low_count": 15,
      "mid_count": 13,
      "high_count": 13,
      "low_decreasing_count": 5
    },
    {
      "year": 2002,
      "low": -29.75,
      "mid": -33.92,
      "high": -34.8,
      "low_decreasing": -18.54,
      "spy": -51.25,
      "low_count": 27,
      "mid_count": 26,
      "high_count": 20,
      "low_decreasing_count": 13
    },
    {
      "year": 2003,
      "low": 39.63,
      "mid": 32.15,
      "high": 43.14,
      "low_decreasing": 37.28,
      "spy": 54.77,
      "low_count": 29,
      "mid_count": 28,
      "high_count": 25,
      "low_decreasing_count": 15
    },
    {
      "year": 2004,
      "low": 9.67,
      "mid": 16.01,
      "high": 9.08,
      "low_decreasing": 5.53,
      "spy": 8.33,
      "low_count": 38,
      "mid_count": 31,
      "high_count": 35,
      "low_decreasing_count": 22
    },
    {
      "year": 2005,
      "low": 30.12,
      "mid": 42.53,
      "high": 36.81,
      "low_decreasing": 28.17,
      "spy": 38.76,
      "low_count": 53,
      "mid_count": 38,
      "high_count": 35,
      "low_decreasing_count": 26
    },
    {
      "year": 2006,
      "low": 15.76,
      "mid": 10.35,
      "high": 18.29,
      "low_decreasing": 13.09,
      "spy": 15.16,
      "low_count": 62,
      "mid_count": 34,
      "high_count": 46,
      "low_decreasing_count": 38
    },
    {
      "year": 2007,
      "low": -6.06,
      "mid": -10.42,
      "high": -7.6,
      "low_decreasing": -2.73,
      "spy": -2.3,
      "low_count": 66,
      "mid_count": 52,
      "high_count": 52,
      "low_decreasing_count": 28
    },
    {
      "year": 2008,
      "low": -33.89,
      "mid": -31.85,
      "high": -30.69,
      "low_decreasing": -35.42,
      "spy": -35.35,
      "low_count": 103,
      "mid_count": 96,
      "high_count": 80,
      "low_decreasing_count": 52
    },
    {
      "year": 2009,
      "low": 47.04,
      "mid": 57.43,
      "high": 53.14,
      "low_decreasing": 47.5,
      "spy": 42.68,
      "low_count": 85,
      "mid_count": 82,
      "high_count": 78,
      "low_decreasing_count": 57
    },
    {
      "year": 2010,
      "low": 20.09,
      "mid": 11.68,
      "high": 17.22,
      "low_decreasing": 21.41,
      "spy": 14.76,
      "low_count": 90,
      "mid_count": 99,
      "high_count": 86,
      "low_decreasing_count": 46
    },
    {
      "year": 2011,
      "low": 1.85,
      "mid": 1.8,
      "high": 2.8,
      "low_decreasing": 1.95,
      "spy": -1.65,
      "low_count": 105,
      "mid_count": 95,
      "high_count": 94,
      "low_decreasing_count": 74
    },
    {
      "year": 2012,
      "low": 13.97,
      "mid": 11.13,
      "high": 16.2,
      "low_decreasing": 13.15,
      "spy": 12.57,
      "low_count": 117,
      "mid_count": 92,
      "high_count": 90,
      "low_decreasing_count": 61
    },
    {
      "year": 2013,
      "low": 21.77,
      "mid": 15.69,
      "high": 19.98,
      "low_decreasing": 19.37,
      "spy": 21.14,
      "low_count": 108,
      "mid_count": 105,
      "high_count": 94,
      "low_decreasing_count": 53
    },
    {
      "year": 2014,
      "low": 26.9,
      "mid": 17.6,
      "high": 20.84,
      "low_decreasing": 30.24,
      "spy": 24.36,
      "low_count": 112,
      "mid_count": 100,
      "high_count": 106,
      "low_decreasing_count": 66
    },
    {
      "year": 2015,
      "low": -3.31,
      "mid": -4.6,
      "high": -4.79,
      "low_decreasing": -2.13,
      "spy": -17.93,
      "low_count": 126,
      "mid_count": 108,
      "high_count": 113,
      "low_decreasing_count": 65
    },
    {
      "year": 2016,
      "low": 21.34,
      "mid": 21.4,
      "high": 21.22,
      "low_decreasing": 22.47,
      "spy": 24.79,
      "low_count": 136,
      "mid_count": 115,
      "high_count": 113,
      "low_decreasing_count": 82
    },
    {
      "year": 2017,
      "low": 3.6,
      "mid": 2.63,
      "high": 8.44,
      "low_decreasing": 0.72,
      "spy": -2.08,
      "low_count": 136,
      "mid_count": 121,
      "high_count": 126,
      "low_decreasing_count": 84
    },
    {
      "year": 2018,
      "low": 7.08,
      "mid": 3.45,
      "high": 5.85,
      "low_decreasing": 5.87,
      "spy": -2.06,
      "low_count": 145,
      "mid_count": 130,
      "high_count": 130,
      "low_decreasing_count": 81
    },
    {
      "year": 2019,
      "low": -15.77,
      "mid": -13.61,
      "high": -13.14,
      "low_decreasing": -16.44,
      "spy": -18.58,
      "low_count": 145,
      "mid_count": 116,
      "high_count": 126,
      "low_decreasing_count": 75
    },
    {
      "year": 2020,
      "low": 53.95,
      "mid": 68.63,
      "high": 61.97,
      "low_decreasing": 53.58,
      "spy": 58.95,
      "low_count": 151,
      "mid_count": 121,
      "high_count": 139,
      "low_decreasing_count": 72
    },
    {
      "year": 2021,
      "low": -1.63,
      "mid": 7.65,
      "high": 5.6,
      "low_decreasing": -3.61,
      "spy": -4.57,
      "low_count": 168,
      "mid_count": 138,
      "high_count": 155,
      "low_decreasing_count": 95
    },
    {
      "year": 2022,
      "low": -6.45,
      "mid": -7.78,
      "high": -2.85,
      "low_decreasing": -4.68,
      "spy": 7.32,
      "low_count": 160,
      "mid_count": 136,
      "high_count": 155,
      "low_decreasing_count": 107
    },
    {
      "year": 2023,
      "low": 10.67,
      "mid": 4.96,
      "high": 5.09,
      "low_decreasing": 10.15,
      "spy": 17.34,
      "low_count": 151,
      "mid_count": 113,
      "high_count": 149,
      "low_decreasing_count": 71
    },
    {
      "year": 2024,
      "low": 7.19,
      "mid": 0.36,
      "high": 2.4,
      "low_decreasing": 5.72,
      "spy": 22.47,
      "low_count": 139,
      "mid_count": 89,
      "high_count": 137,
      "low_decreasing_count": 75
    }
  ],
  "benchmark": {
    "symbol": "^GDAXI",
    "name": "DAX"
  },
  "execution": "next-day close (MOC)"
}