{
  "ASX": {
    "universe": "ASX",
    "n_periods": 25,
    "years": 25.0,
    "frequency": "annual",
    "cash_periods": 3,
    "invested_periods": 22,
    "avg_stocks_when_invested": 19.5,
    "portfolio": {
      "total_return": 347.59,
      "cagr": 6.18,
      "max_drawdown": -46.11,
      "annualized_volatility": 16.12,
      "sharpe_ratio": 0.166,
      "sortino_ratio": 0.28,
      "calmar_ratio": 0.134,
      "var_95": -26.11,
      "max_consecutive_losses": 2,
      "pct_negative_periods": 20.0
    },
    "spy": {
      "total_return": 159.9,
      "cagr": 3.89,
      "max_drawdown": -38.09,
      "annualized_volatility": 12.77,
      "sharpe_ratio": 0.031,
      "sortino_ratio": 0.044,
      "calmar_ratio": 0.102,
      "var_95": -18.66,
      "max_consecutive_losses": 2,
      "pct_negative_periods": 32.0
    },
    "comparison": {
      "excess_cagr": 2.28,
      "win_rate": 56.0,
      "information_ratio": 0.316,
      "tracking_error": 8.58,
      "up_capture": 118.09,
      "down_capture": 66.01,
      "beta": 1.071,
      "alpha": 2.26
    },
    "excess_cagr": 2.28,
    "win_rate_vs_spy": 56.0,
    "annual_returns": [
      {
        "year": 2000,
        "portfolio": 0.0,
        "spy": 3.94,
        "excess": -3.94
      },
      {
        "year": 2001,
        "portfolio": 0.0,
        "spy": -6.58,
        "excess": 6.58
      },
      {
        "year": 2002,
        "portfolio": 10.97,
        "spy": -5.61,
        "excess": 16.58
      },
      {
        "year": 2003,
        "portfolio": 0.0,
        "spy": 16.57,
        "excess": -16.57
      },
      {
        "year": 2004,
        "portfolio": 30.7,
        "spy": 21.15,
        "excess": 9.55
      },
      {
        "year": 2005,
        "portfolio": 32.04,
        "spy": 18.92,
        "excess": 13.12
      },
      {
        "year": 2006,
        "portfolio": 28.5,
        "spy": 23.0,
        "excess": 5.5
      },
      {
        "year": 2007,
        "portfolio": -26.11,
        "spy": -18.66,
        "excess": -7.45
      },
      {
        "year": 2008,
        "portfolio": -27.07,
        "spy": -23.9,
        "excess": -3.17
      },
      {
        "year": 2009,
        "portfolio": 17.08,
        "spy": 9.32,
        "excess": 7.76
      },
      {
        "year": 2010,
        "portfolio": 2.18,
        "spy": 8.78,
        "excess": -6.6
      },
      {
        "year": 2011,
        "portfolio": -6.65,
        "spy": -10.36,
        "excess": 3.71
      },
      {
        "year": 2012,
        "portfolio": 16.59,
        "spy": 16.96,
        "excess": -0.38
      },
      {
        "year": 2013,
        "portfolio": 10.72,
        "spy": 12.85,
        "excess": -2.14
      },
      {
        "year": 2014,
        "portfolio": 15.19,
        "spy": 2.65,
        "excess": 12.54
      },
      {
        "year": 2015,
        "portfolio": 7.7,
        "spy": -5.68,
        "excess": 13.38
      },
      {
        "year": 2016,
        "portfolio": 4.32,
        "spy": 7.62,
        "excess": -3.31
      },
      {
        "year": 2017,
        "portfolio": 12.9,
        "spy": 8.68,
        "excess": 4.22
      },
      {
        "year": 2018,
        "portfolio": 8.64,
        "spy": 7.7,
        "excess": 0.95
      },
      {
        "year": 2019,
        "portfolio": -5.79,
        "spy": -9.33,
        "excess": 3.54
      },
      {
        "year": 2020,
        "portfolio": 38.8,
        "spy": 21.15,
        "excess": 17.65
      },
      {
        "year": 2021,
        "portfolio": -12.22,
        "spy": -9.52,
        "excess": -2.7
      },
      {
        "year": 2022,
        "portfolio": 8.56,
        "spy": 9.58,
        "excess": -1.02
      },
      {
        "year": 2023,
        "portfolio": 15.6,
        "spy": 6.52,
        "excess": 9.09
      },
      {
        "year": 2024,
        "portfolio": 2.4,
        "spy": 11.4,
        "excess": -9.0
      }
    ]
  },
  "BSE_NSE": {
    "universe": "India",
    "n_periods": 25,
    "years": 25.0,
    "frequency": "annual",
    "cash_periods": 5,
    "invested_periods": 20,
    "avg_stocks_when_invested": 24.1,
    "portfolio": {
      "total_return": 2743.27,
      "cagr": 14.33,
      "max_drawdown": -19.79,
      "annualized_volatility": 26.09,
      "sharpe_ratio": 0.3,
      "sortino_ratio": 0.932,
      "calmar_ratio": 0.724,
      "var_95": -12.21,
      "max_consecutive_losses": 2,
      "pct_negative_periods": 24.0
    },
    "spy": {
      "total_return": 1621.57,
      "cagr": 12.06,
      "max_drawdown": -32.2,
      "annualized_volatility": 19.59,
      "sharpe_ratio": 0.284,
      "sortino_ratio": 0.6,
      "calmar_ratio": 0.374,
      "var_95": -9.98,
      "max_consecutive_losses": 2,
      "pct_negative_periods": 24.0
    },
    "comparison": {
      "excess_cagr": 2.27,
      "win_rate": 52.0,
      "information_ratio": 0.138,
      "tracking_error": 23.31,
      "up_capture": 107.5,
      "down_capture": 16.92,
      "beta": 0.679,
      "alpha": 4.05
    },
    "excess_cagr": 2.27,
    "win_rate_vs_spy": 52.0,
    "annual_returns": [
      {
        "year": 2000,
        "portfolio": 0.0,
        "spy": -29.29,
        "excess": 29.29
      },
      {
        "year": 2001,
        "portfolio": 0.0,
        "spy": -4.12,
        "excess": 4.12
      },
      {
        "year": 2002,
        "portfolio": 0.0,
        "spy": 9.63,
        "excess": -9.63
      },
      {
        "year": 2003,
        "portfolio": 0.0,
        "spy": 35.24,
        "excess": -35.24
      },
      {
        "year": 2004,
        "portfolio": 0.0,
        "spy": 49.41,
        "excess": -49.41
      },
      {
        "year": 2005,
        "portfolio": 39.64,
        "spy": 46.97,
        "excess": -7.33
      },
      {
        "year": 2006,
        "portfolio": 15.62,
        "spy": 37.11,
        "excess": -21.49
      },
      {
        "year": 2007,
        "portfolio": -12.21,
        "spy": -6.82,
        "excess": -5.4
      },
      {
        "year": 2008,
        "portfolio": 19.82,
        "spy": 7.27,
        "excess": 12.54
      },
      {
        "year": 2009,
        "portfolio": 65.07,
        "spy": 19.12,
        "excess": 45.95
      },
      {
        "year": 2010,
        "portfolio": -5.52,
        "spy": 7.75,
        "excess": -13.27
      },
      {
        "year": 2011,
        "portfolio": 3.65,
        "spy": -7.52,
        "excess": 11.17
      },
      {
        "year": 2012,
        "portfolio": -11.66,
        "spy": 11.87,
        "excess": -23.52
      },
      {
        "year": 2013,
        "portfolio": 46.02,
        "spy": 32.77,
        "excess": 13.25
      },
      {
        "year": 2014,
        "portfolio": 38.15,
        "spy": 8.14,
        "excess": 30.01
      },
      {
        "year": 2015,
        "portfolio": 12.11,
        "spy": -2.39,
        "excess": 14.5
      },
      {
        "year": 2016,
        "portfolio": 39.41,
        "spy": 14.45,
        "excess": 24.96
      },
      {
        "year": 2017,
        "portfolio": 11.88,
        "spy": 12.95,
        "excess": -1.07
      },
      {
        "year": 2018,
        "portfolio": -7.03,
        "spy": 12.91,
        "excess": -19.94
      },
      {
        "year": 2019,
        "portfolio": -13.72,
        "spy": -9.98,
        "excess": -3.74
      },
      {
        "year": 2020,
        "portfolio": 77.43,
        "spy": 46.43,
        "excess": 31.0
      },
      {
        "year": 2021,
        "portfolio": 9.47,
        "spy": 1.43,
        "excess": 8.04
      },
      {
        "year": 2022,
        "portfolio": 48.29,
        "spy": 22.49,
        "excess": 25.81
      },
      {
        "year": 2023,
        "portfolio": 51.26,
        "spy": 21.83,
        "excess": 29.43
      },
      {
        "year": 2024,
        "portfolio": -4.9,
        "spy": 5.0,
        "excess": -9.89
      }
    ]
  },
  "HKSE": {
    "universe": "HKSE",
    "n_periods": 25,
    "years": 25.0,
    "frequency": "annual",
    "cash_periods": 0,
    "invested_periods": 25,
    "avg_stocks_when_invested": 19.6,
    "portfolio": {
      "total_return": 279.34,
      "cagr": 5.48,
      "max_drawdown": -33.93,
      "annualized_volatility": 19.71,
      "sharpe_ratio": 0.126,
      "sortino_ratio": 0.242,
      "calmar_ratio": 0.161,
      "var_95": -18.31,
      "max_consecutive_losses": 2,
      "pct_negative_periods": 40.0
    },
    "spy": {
      "total_return": 50.22,
      "cagr": 1.64,
      "max_drawdown": -40.45,
      "annualized_volatility": 17.75,
      "sharpe_ratio": -0.077,
      "sortino_ratio": -0.114,
      "calmar_ratio": 0.041,
      "var_95": -20.43,
      "max_consecutive_losses": 3,
      "pct_negative_periods": 44.0
    },
    "comparison": {
      "excess_cagr": 3.84,
      "win_rate": 60.0,
      "information_ratio": 0.288,
      "tracking_error": 14.15,
      "up_capture": 118.76,
      "down_capture": 62.0,
      "beta": 0.799,
      "alpha": 3.56
    },
    "excess_cagr": 3.84,
    "win_rate_vs_spy": 60.0,
    "annual_returns": [
      {
        "year": 2000,
        "portfolio": 0.27,
        "spy": -18.23,
        "excess": 18.5
      },
      {
        "year": 2001,
        "portfolio": -5.95,
        "spy": -20.43,
        "excess": 14.47
      },
      {
        "year": 2002,
        "portfolio": -0.66,
        "spy": -8.47,
        "excess": 7.81
      },
      {
        "year": 2003,
        "portfolio": 33.68,
        "spy": 27.26,
        "excess": 6.42
      },
      {
        "year": 2004,
        "portfolio": 13.01,
        "spy": 16.02,
        "excess": -3.01
      },
      {
        "year": 2005,
        "portfolio": 9.06,
        "spy": 15.16,
        "excess": -6.1
      },
      {
        "year": 2006,
        "portfolio": 56.5,
        "spy": 35.67,
        "excess": 20.82
      },
      {
        "year": 2007,
        "portfolio": -31.01,
        "spy": -2.02,
        "excess": -29.0
      },
      {
        "year": 2008,
        "portfolio": -4.23,
        "spy": -16.25,
        "excess": 12.02
      },
      {
        "year": 2009,
        "portfolio": 33.59,
        "spy": 9.5,
        "excess": 24.08
      },
      {
        "year": 2010,
        "portfolio": 13.2,
        "spy": 14.39,
        "excess": -1.2
      },
      {
        "year": 2011,
        "portfolio": -14.83,
        "spy": -13.33,
        "excess": -1.5
      },
      {
        "year": 2012,
        "portfolio": 11.98,
        "spy": 4.68,
        "excess": 7.3
      },
      {
        "year": 2013,
        "portfolio": 13.21,
        "spy": 13.99,
        "excess": -0.79
      },
      {
        "year": 2014,
        "portfolio": 22.09,
        "spy": 11.6,
        "excess": 10.49
      },
      {
        "year": 2015,
        "portfolio": -12.97,
        "spy": -19.87,
        "excess": 6.9
      },
      {
        "year": 2016,
        "portfolio": 10.81,
        "spy": 22.44,
        "excess": -11.63
      },
      {
        "year": 2017,
        "portfolio": 38.67,
        "spy": 10.71,
        "excess": 27.96
      },
      {
        "year": 2018,
        "portfolio": -7.56,
        "spy": 1.16,
        "excess": -8.72
      },
      {
        "year": 2019,
        "portfolio": -18.31,
        "spy": -12.99,
        "excess": -5.32
      },
      {
        "year": 2020,
        "portfolio": 18.91,
        "spy": 12.68,
        "excess": 6.23
      },
      {
        "year": 2021,
        "portfolio": -7.35,
        "spy": -22.89,
        "excess": 15.54
      },
      {
        "year": 2022,
        "portfolio": -4.75,
        "spy": -11.56,
        "excess": 6.81
      },
      {
        "year": 2023,
        "portfolio": 4.31,
        "spy": -7.96,
        "excess": 12.28
      },
      {
        "year": 2024,
        "portfolio": 7.89,
        "spy": 36.31,
        "excess": -28.42
      }
    ]
  },
  "JPX": {
    "universe": "JPX",
    "n_periods": 25,
    "years": 25.0,
    "frequency": "annual",
    "cash_periods": 4,
    "invested_periods": 21,
    "avg_stocks_when_invested": 27.7,
    "portfolio": {
      "total_return": 441.13,
      "cagr": 6.99,
      "max_drawdown": -29.29,
      "annualized_volatility": 18.53,
      "sharpe_ratio": 0.372,
      "sortino_ratio": 1.202,
      "calmar_ratio": 0.239,
      "var_95": -13.69,
      "max_consecutive_losses": 3,
      "pct_negative_periods": 32.0
    },
    "spy": {
      "total_return": 125.74,
      "cagr": 3.31,
      "max_drawdown": -50.38,
      "annualized_volatility": 22.16,
      "sharpe_ratio": 0.145,
      "sortino_ratio": 0.279,
      "calmar_ratio": 0.066,
      "var_95": -26.78,
      "max_consecutive_losses": 3,
      "pct_negative_periods": 48.0
    },
    "comparison": {
      "excess_cagr": 3.68,
      "win_rate": 60.0,
      "information_ratio": 0.262,
      "tracking_error": 10.96,
      "up_capture": 92.33,
      "down_capture": 39.67,
      "beta": 0.727,
      "alpha": 4.55
    },
    "excess_cagr": 3.68,
    "win_rate_vs_spy": 60.0,
    "annual_returns": [
      {
        "year": 2000,
        "portfolio": 0.0,
        "spy": -27.61,
        "excess": 27.61
      },
      {
        "year": 2001,
        "portfolio": 0.0,
        "spy": -17.86,
        "excess": 17.86
      },
      {
        "year": 2002,
        "portfolio": 0.0,
        "spy": -8.1,
        "excess": 8.1
      },
      {
        "year": 2003,
        "portfolio": 0.0,
        "spy": 21.78,
        "excess": -21.78
      },
      {
        "year": 2004,
        "portfolio": 5.58,
        "spy": -0.6,
        "excess": 6.18
      },
      {
        "year": 2005,
        "portfolio": 37.91,
        "spy": 33.64,
        "excess": 4.26
      },
      {
        "year": 2006,
        "portfolio": 6.69,
        "spy": 16.53,
        "excess": -9.85
      },
      {
        "year": 2007,
        "portfolio": -13.69,
        "spy": -26.78,
        "excess": 13.09
      },
      {
        "year": 2008,
        "portfolio": -13.56,
        "spy": -25.67,
        "excess": 12.11
      },
      {
        "year": 2009,
        "portfolio": -0.92,
        "spy": -6.81,
        "excess": 5.89
      },
      {
        "year": 2010,
        "portfolio": 1.01,
        "spy": 8.27,
        "excess": -7.26
      },
      {
        "year": 2011,
        "portfolio": -5.29,
        "spy": -9.65,
        "excess": 4.36
      },
      {
        "year": 2012,
        "portfolio": 49.58,
        "spy": 56.59,
        "excess": -7.01
      },
      {
        "year": 2013,
        "portfolio": 21.77,
        "spy": 9.02,
        "excess": 12.75
      },
      {
        "year": 2014,
        "portfolio": 37.16,
        "spy": 33.52,
        "excess": 3.64
      },
      {
        "year": 2015,
        "portfolio": -14.48,
        "spy": -23.13,
        "excess": 8.65
      },
      {
        "year": 2016,
        "portfolio": 40.0,
        "spy": 27.13,
        "excess": 12.87
      },
      {
        "year": 2017,
        "portfolio": 6.94,
        "spy": 8.76,
        "excess": -1.82
      },
      {
        "year": 2018,
        "portfolio": -4.58,
        "spy": -0.26,
        "excess": -4.31
      },
      {
        "year": 2019,
        "portfolio": 10.6,
        "spy": 1.8,
        "excess": 8.8
      },
      {
        "year": 2020,
        "portfolio": 35.81,
        "spy": 29.97,
        "excess": 5.84
      },
      {
        "year": 2021,
        "portfolio": -13.15,
        "spy": -9.14,
        "excess": -4.02
      },
      {
        "year": 2022,
        "portfolio": 15.55,
        "spy": 29.06,
        "excess": -13.51
      },
      {
        "year": 2023,
        "portfolio": 9.2,
        "spy": 18.73,
        "excess": -9.53
      },
      {
        "year": 2024,
        "portfolio": -1.94,
        "spy": -0.78,
        "excess": -1.16
      }
    ]
  },
  "KSC": {
    "universe": "KSC",
    "n_periods": 25,
    "years": 25.0,
    "frequency": "annual",
    "cash_periods": 10,
    "invested_periods": 15,
    "avg_stocks_when_invested": 24.1,
    "portfolio": {
      "total_return": 270.46,
      "cagr": 5.38,
      "max_drawdown": -24.66,
      "annualized_volatility": 13.68,
      "sharpe_ratio": 0.174,
      "sortino_ratio": 0.392,
      "calmar_ratio": 0.218,
      "var_95": -5.88,
      "max_consecutive_losses": 2,
      "pct_negative_periods": 16.0
    },
    "spy": {
      "total_return": 268.18,
      "cagr": 5.35,
      "max_drawdown": -29.91,
      "annualized_volatility": 20.3,
      "sharpe_ratio": 0.116,
      "sortino_ratio": 0.211,
      "calmar_ratio": 0.179,
      "var_95": -28.55,
      "max_consecutive_losses": 2,
      "pct_negative_periods": 36.0
    },
    "comparison": {
      "excess_cagr": 0.03,
      "win_rate": 56.0,
      "information_ratio": -0.055,
      "tracking_error": 18.52,
      "up_capture": 59.57,
      "down_capture": 19.63,
      "beta": 0.311,
      "alpha": 1.65
    },
    "excess_cagr": 0.03,
    "win_rate_vs_spy": 56.0,
    "annual_returns": [
      {
        "year": 2000,
        "portfolio": 0.0,
        "spy": -28.55,
        "excess": 28.55
      },
      {
        "year": 2001,
        "portfolio": 0.0,
        "spy": 25.05,
        "excess": -25.05
      },
      {
        "year": 2002,
        "portfolio": 0.0,
        "spy": -8.1,
        "excess": 8.1
      },
      {
        "year": 2003,
        "portfolio": 0.0,
        "spy": 10.15,
        "excess": -10.15
      },
      {
        "year": 2004,
        "portfolio": 0.0,
        "spy": 35.25,
        "excess": -35.25
      },
      {
        "year": 2005,
        "portfolio": 0.0,
        "spy": 26.71,
        "excess": -26.71
      },
      {
        "year": 2006,
        "portfolio": 0.0,
        "spy": 36.82,
        "excess": -36.82
      },
      {
        "year": 2007,
        "portfolio": 0.0,
        "spy": -8.34,
        "excess": 8.34
      },
      {
        "year": 2008,
        "portfolio": 0.0,
        "spy": -13.06,
        "excess": 13.06
      },
      {
        "year": 2009,
        "portfolio": 0.0,
        "spy": 18.44,
        "excess": -18.44
      },
      {
        "year": 2010,
        "portfolio": 26.81,
        "spy": 28.32,
        "excess": -1.51
      },
      {
        "year": 2011,
        "portfolio": 6.93,
        "spy": -13.69,
        "excess": 20.62
      },
      {
        "year": 2012,
        "portfolio": 20.59,
        "spy": 0.18,
        "excess": 20.41
      },
      {
        "year": 2013,
        "portfolio": 25.4,
        "spy": 8.64,
        "excess": 16.76
      },
      {
        "year": 2014,
        "portfolio": 27.34,
        "spy": 4.57,
        "excess": 22.77
      },
      {
        "year": 2015,
        "portfolio": 2.67,
        "spy": -5.32,
        "excess": 7.99
      },
      {
        "year": 2016,
        "portfolio": 3.27,
        "spy": 20.01,
        "excess": -16.73
      },
      {
        "year": 2017,
        "portfolio": -4.12,
        "spy": -5.13,
        "excess": 1.01
      },
      {
        "year": 2018,
        "portfolio": -5.88,
        "spy": -6.58,
        "excess": 0.7
      },
      {
        "year": 2019,
        "portfolio": 11.55,
        "spy": 0.63,
        "excess": 10.92
      },
      {
        "year": 2020,
        "portfolio": 40.0,
        "spy": 53.69,
        "excess": -13.69
      },
      {
        "year": 2021,
        "portfolio": -22.9,
        "spy": -29.91,
        "excess": 7.01
      },
      {
        "year": 2022,
        "portfolio": -2.29,
        "spy": 13.13,
        "excess": -15.42
      },
      {
        "year": 2023,
        "portfolio": 2.51,
        "spy": 6.85,
        "excess": -4.34
      },
      {
        "year": 2024,
        "portfolio": 22.94,
        "spy": 10.58,
        "excess": 12.36
      }
    ]
  },
  "LSE": {
    "universe": "LSE",
    "n_periods": 25,
    "years": 25.0,
    "frequency": "annual",
    "cash_periods": 0,
    "invested_periods": 25,
    "avg_stocks_when_invested": 19.0,
    "portfolio": {
      "total_return": 1240.11,
      "cagr": 10.94,
      "max_drawdown": -20.33,
      "annualized_volatility": 15.42,
      "sharpe_ratio": 0.482,
      "sortino_ratio": 1.236,
      "calmar_ratio": 0.538,
      "var_95": -12.33,
      "max_consecutive_losses": 2,
      "pct_negative_periods": 20.0
    },
    "spy": {
      "total_return": 35.61,
      "cagr": 1.23,
      "max_drawdown": -38.07,
      "annualized_volatility": 12.91,
      "sharpe_ratio": -0.176,
      "sortino_ratio": -0.217,
      "calmar_ratio": 0.032,
      "var_95": -20.46,
      "max_consecutive_losses": 3,
      "pct_negative_periods": 36.0
    },
    "comparison": {
      "excess_cagr": 9.71,
      "win_rate": 96.0,
      "information_ratio": 1.168,
      "tracking_error": 8.48,
      "up_capture": 185.29,
      "down_capture": 2.71,
      "beta": 0.997,
      "alpha": 9.71
    },
    "excess_cagr": 9.71,
    "win_rate_vs_spy": 96.0,
    "annual_returns": [
      {
        "year": 2000,
        "portfolio": 11.08,
        "spy": -11.65,
        "excess": 22.73
      },
      {
        "year": 2001,
        "portfolio": -6.85,
        "spy": -20.46,
        "excess": 13.62
      },
      {
        "year": 2002,
        "portfolio": -7.22,
        "spy": -11.87,
        "excess": 4.65
      },
      {
        "year": 2003,
        "portfolio": 19.4,
        "spy": 10.0,
        "excess": 9.41
      },
      {
        "year": 2004,
        "portfolio": 21.26,
        "spy": 17.63,
        "excess": 3.63
      },
      {
        "year": 2005,
        "portfolio": 21.06,
        "spy": 13.5,
        "excess": 7.56
      },
      {
        "year": 2006,
        "portfolio": 27.03,
        "spy": 12.0,
        "excess": 15.03
      },
      {
        "year": 2007,
        "portfolio": -13.5,
        "spy": -17.67,
        "excess": 4.17
      },
      {
        "year": 2008,
        "portfolio": -7.9,
        "spy": -21.97,
        "excess": 14.07
      },
      {
        "year": 2009,
        "portfolio": 18.92,
        "spy": 14.26,
        "excess": 4.66
      },
      {
        "year": 2010,
        "portfolio": 46.87,
        "spy": 24.38,
        "excess": 22.5
      },
      {
        "year": 2011,
        "portfolio": 1.24,
        "spy": -6.26,
        "excess": 7.5
      },
      {
        "year": 2012,
        "portfolio": 37.48,
        "spy": 11.76,
        "excess": 25.72
      },
      {
        "year": 2013,
        "portfolio": 15.06,
        "spy": 8.13,
        "excess": 6.93
      },
      {
        "year": 2014,
        "portfolio": 7.6,
        "spy": -2.73,
        "excess": 10.33
      },
      {
        "year": 2015,
        "portfolio": 12.12,
        "spy": -1.63,
        "excess": 13.75
      },
      {
        "year": 2016,
        "portfolio": 15.4,
        "spy": 13.11,
        "excess": 2.29
      },
      {
        "year": 2017,
        "portfolio": 5.67,
        "spy": 2.31,
        "excess": 3.35
      },
      {
        "year": 2018,
        "portfolio": 10.26,
        "spy": 0.15,
        "excess": 10.11
      },
      {
        "year": 2019,
        "portfolio": 0.41,
        "spy": -17.45,
        "excess": 17.85
      },
      {
        "year": 2020,
        "portfolio": 35.35,
        "spy": 14.15,
        "excess": 21.2
      },
      {
        "year": 2021,
        "portfolio": -12.33,
        "spy": 1.54,
        "excess": -13.86
      },
      {
        "year": 2022,
        "portfolio": 5.92,
        "spy": 4.07,
        "excess": 1.85
      },
      {
        "year": 2023,
        "portfolio": 19.64,
        "spy": 7.89,
        "excess": 11.75
      },
      {
        "year": 2024,
        "portfolio": 14.88,
        "spy": 8.05,
        "excess": 6.84
      }
    ]
  },
  "NYSE_NASDAQ_AMEX": {
    "universe": "US_MAJOR",
    "n_periods": 25,
    "years": 25.0,
    "frequency": "annual",
    "cash_periods": 0,
    "invested_periods": 25,
    "avg_stocks_when_invested": 26.2,
    "portfolio": {
      "total_return": 1921.17,
      "cagr": 12.78,
      "max_drawdown": -28.25,
      "annualized_volatility": 15.47,
      "sharpe_ratio": 0.697,
      "sortino_ratio": 2.038,
      "calmar_ratio": 0.452,
      "var_95": -14.14,
      "max_consecutive_losses": 2,
      "pct_negative_periods": 16.0
    },
    "spy": {
      "total_return": 561.67,
      "cagr": 7.85,
      "max_drawdown": -38.01,
      "annualized_volatility": 16.63,
      "sharpe_ratio": 0.352,
      "sortino_ratio": 0.628,
      "calmar_ratio": 0.207,
      "var_95": -22.45,
      "max_consecutive_losses": 2,
      "pct_negative_periods": 20.0
    },
    "comparison": {
      "excess_cagr": 4.93,
      "win_rate": 64.0,
      "information_ratio": 0.411,
      "tracking_error": 11.3,
      "up_capture": 111.77,
      "down_capture": 12.82,
      "beta": 0.702,
      "alpha": 6.67
    },
    "excess_cagr": 4.93,
    "win_rate_vs_spy": 64.0,
    "annual_returns": [
      {
        "year": 2000,
        "portfolio": 19.64,
        "spy": -14.78,
        "excess": 34.42
      },
      {
        "year": 2001,
        "portfolio": 5.73,
        "spy": -22.45,
        "excess": 28.18
      },
      {
        "year": 2002,
        "portfolio": 13.81,
        "spy": 6.86,
        "excess": 6.95
      },
      {
        "year": 2003,
        "portfolio": 21.17,
        "spy": 14.93,
        "excess": 6.24
      },
      {
        "year": 2004,
        "portfolio": 26.81,
        "spy": 8.87,
        "excess": 17.94
      },
      {
        "year": 2005,
        "portfolio": 16.65,
        "spy": 7.99,
        "excess": 8.66
      },
      {
        "year": 2006,
        "portfolio": 24.02,
        "spy": 20.95,
        "excess": 3.08
      },
      {
        "year": 2007,
        "portfolio": -16.43,
        "spy": -15.2,
        "excess": -1.24
      },
      {
        "year": 2008,
        "portfolio": -14.14,
        "spy": -26.9,
        "excess": 12.76
      },
      {
        "year": 2009,
        "portfolio": 26.93,
        "spy": 15.98,
        "excess": 10.95
      },
      {
        "year": 2010,
        "portfolio": 30.46,
        "spy": 33.55,
        "excess": -3.09
      },
      {
        "year": 2011,
        "portfolio": 5.8,
        "spy": 4.19,
        "excess": 1.61
      },
      {
        "year": 2012,
        "portfolio": 23.19,
        "spy": 20.74,
        "excess": 2.45
      },
      {
        "year": 2013,
        "portfolio": 22.92,
        "spy": 24.74,
        "excess": -1.82
      },
      {
        "year": 2014,
        "portfolio": 0.69,
        "spy": 7.18,
        "excess": -6.49
      },
      {
        "year": 2015,
        "portfolio": -3.26,
        "spy": 2.71,
        "excess": -5.97
      },
      {
        "year": 2016,
        "portfolio": 34.1,
        "spy": 18.58,
        "excess": 15.52
      },
      {
        "year": 2017,
        "portfolio": 21.37,
        "spy": 14.34,
        "excess": 7.04
      },
      {
        "year": 2018,
        "portfolio": 1.68,
        "spy": 11.2,
        "excess": -9.52
      },
      {
        "year": 2019,
        "portfolio": 8.04,
        "spy": 7.43,
        "excess": 0.61
      },
      {
        "year": 2020,
        "portfolio": 50.56,
        "spy": 40.98,
        "excess": 9.58
      },
      {
        "year": 2021,
        "portfolio": -6.33,
        "spy": -10.68,
        "excess": 4.35
      },
      {
        "year": 2022,
        "portfolio": 7.11,
        "spy": 18.08,
        "excess": -10.98
      },
      {
        "year": 2023,
        "portfolio": 14.54,
        "spy": 25.44,
        "excess": -10.9
      },
      {
        "year": 2024,
        "portfolio": 10.12,
        "spy": 14.42,
        "excess": -4.3
      }
    ]
  },
  "SAO": {
    "universe": "SAO",
    "n_periods": 25,
    "years": 25.0,
    "frequency": "annual",
    "cash_periods": 4,
    "invested_periods": 21,
    "avg_stocks_when_invested": 20.9,
    "portfolio": {
      "total_return": 1137.25,
      "cagr": 10.59,
      "max_drawdown": -9.49,
      "annualized_volatility": 16.61,
      "sharpe_ratio": 0.005,
      "sortino_ratio": 0.01,
      "calmar_ratio": 1.116,
      "var_95": -6.62,
      "max_consecutive_losses": 3,
      "pct_negative_periods": 20.0
    },
    "spy": {
      "total_return": 704.74,
      "cagr": 8.7,
      "max_drawdown": -38.45,
      "annualized_volatility": 23.94,
      "sharpe_ratio": -0.075,
      "sortino_ratio": -0.118,
      "calmar_ratio": 0.226,
      "var_95": -22.98,
      "max_consecutive_losses": 2,
      "pct_negative_periods": 36.0
    },
    "comparison": {
      "excess_cagr": 1.89,
      "win_rate": 60.0,
      "information_ratio": 0.024,
      "tracking_error": 22.32,
      "up_capture": 66.23,
      "down_capture": -23.4,
      "beta": 0.306,
      "alpha": 0.64
    },
    "excess_cagr": 1.89,
    "win_rate_vs_spy": 60.0,
    "annual_returns": [
      {
        "year": 2000,
        "portfolio": 0.0,
        "spy": -16.93,
        "excess": 16.93
      },
      {
        "year": 2001,
        "portfolio": 0.0,
        "spy": -25.9,
        "excess": 25.9
      },
      {
        "year": 2002,
        "portfolio": 10.25,
        "spy": 23.49,
        "excess": -13.24
      },
      {
        "year": 2003,
        "portfolio": 0.0,
        "spy": 64.22,
        "excess": -64.22
      },
      {
        "year": 2004,
        "portfolio": 8.45,
        "spy": 14.4,
        "excess": -5.95
      },
      {
        "year": 2005,
        "portfolio": 0.0,
        "spy": 51.44,
        "excess": -51.44
      },
      {
        "year": 2006,
        "portfolio": 59.85,
        "spy": 49.06,
        "excess": 10.79
      },
      {
        "year": 2007,
        "portfolio": 1.5,
        "spy": 6.42,
        "excess": -4.91
      },
      {
        "year": 2008,
        "portfolio": -4.18,
        "spy": -14.07,
        "excess": 9.89
      },
      {
        "year": 2009,
        "portfolio": 3.88,
        "spy": 20.61,
        "excess": -16.73
      },
      {
        "year": 2010,
        "portfolio": 17.67,
        "spy": 2.62,
        "excess": 15.05
      },
      {
        "year": 2011,
        "portfolio": 14.56,
        "spy": -11.51,
        "excess": 26.07
      },
      {
        "year": 2012,
        "portfolio": -0.3,
        "spy": -19.25,
        "excess": 18.94
      },
      {
        "year": 2013,
        "portfolio": -2.61,
        "spy": 19.6,
        "excess": -22.21
      },
      {
        "year": 2014,
        "portfolio": -6.62,
        "spy": -2.52,
        "excess": -4.11
      },
      {
        "year": 2015,
        "portfolio": 5.9,
        "spy": -1.29,
        "excess": 7.19
      },
      {
        "year": 2016,
        "portfolio": 16.14,
        "spy": 21.97,
        "excess": -5.83
      },
      {
        "year": 2017,
        "portfolio": 17.34,
        "spy": 16.5,
        "excess": 0.84
      },
      {
        "year": 2018,
        "portfolio": 31.42,
        "spy": 38.52,
        "excess": -7.1
      },
      {
        "year": 2019,
        "portfolio": 28.12,
        "spy": -5.17,
        "excess": 33.3
      },
      {
        "year": 2020,
        "portfolio": 44.82,
        "spy": 31.89,
        "excess": 12.93
      },
      {
        "year": 2021,
        "portfolio": -9.49,
        "spy": -22.98,
        "excess": 13.49
      },
      {
        "year": 2022,
        "portfolio": 29.1,
        "spy": 21.14,
        "excess": 7.96
      },
      {
        "year": 2023,
        "portfolio": 13.85,
        "spy": 5.53,
        "excess": 8.32
      },
      {
        "year": 2024,
        "portfolio": 11.99,
        "spy": 10.65,
        "excess": 1.33
      }
    ]
  },
  "SAU": {
    "universe": "SAU",
    "n_periods": 25,
    "years": 25.0,
    "frequency": "annual",
    "cash_periods": 9,
    "invested_periods": 16,
    "avg_stocks_when_invested": 23.6,
    "portfolio": {
      "total_return": 88.55,
      "cagr": 2.57,
      "max_drawdown": -39.23,
      "annualized_volatility": 15.96,
      "sharpe_ratio": -0.058,
      "sortino_ratio": -0.104,
      "calmar_ratio": 0.065,
      "var_95": -17.0,
      "max_consecutive_losses": 4,
      "pct_negative_periods": 28.0
    },
    "spy": {
      "total_return": 561.67,
      "cagr": 7.85,
      "max_drawdown": -38.01,
      "annualized_volatility": 16.63,
      "sharpe_ratio": 0.262,
      "sortino_ratio": 0.437,
      "calmar_ratio": 0.207,
      "var_95": -22.45,
      "max_consecutive_losses": 2,
      "pct_negative_periods": 20.0
    },
    "comparison": {
      "excess_cagr": -5.28,
      "win_rate": 32.0,
      "information_ratio": -0.35,
      "tracking_error": 15.68,
      "up_capture": 34.07,
      "down_capture": 18.89,
      "beta": 0.516,
      "alpha": -3.18
    },
    "excess_cagr": -5.28,
    "win_rate_vs_spy": 32.0,
    "annual_returns": [
      {
        "year": 2000,
        "portfolio": 0.0,
        "spy": -14.78,
        "excess": 14.78
      },
      {
        "year": 2001,
        "portfolio": 0.0,
        "spy": -22.45,
        "excess": 22.45
      },
      {
        "year": 2002,
        "portfolio": 0.0,
        "spy": 6.86,
        "excess": -6.86
      },
      {
        "year": 2003,
        "portfolio": 0.0,
        "spy": 14.93,
        "excess": -14.93
      },
      {
        "year": 2004,
        "portfolio": 0.0,
        "spy": 8.87,
        "excess": -8.87
      },
      {
        "year": 2005,
        "portfolio": 0.0,
        "spy": 7.99,
        "excess": -7.99
      },
      {
        "year": 2006,
        "portfolio": 0.0,
        "spy": 20.95,
        "excess": -20.95
      },
      {
        "year": 2007,
        "portfolio": 0.0,
        "spy": -15.2,
        "excess": 15.2
      },
      {
        "year": 2008,
        "portfolio": 0.0,
        "spy": -26.9,
        "excess": 26.9
      },
      {
        "year": 2009,
        "portfolio": 3.89,
        "spy": 15.98,
        "excess": -12.09
      },
      {
        "year": 2010,
        "portfolio": 19.6,
        "spy": 33.55,
        "excess": -13.95
      },
      {
        "year": 2011,
        "portfolio": 9.23,
        "spy": 4.19,
        "excess": 5.05
      },
      {
        "year": 2012,
        "portfolio": 19.61,
        "spy": 20.74,
        "excess": -1.13
      },
      {
        "year": 2013,
        "portfolio": 31.18,
        "spy": 24.74,
        "excess": 6.44
      },
      {
        "year": 2014,
        "portfolio": -3.26,
        "spy": 7.18,
        "excess": -10.44
      },
      {
        "year": 2015,
        "portfolio": -30.21,
        "spy": 2.71,
        "excess": -32.93
      },
      {
        "year": 2016,
        "portfolio": -6.91,
        "spy": 18.58,
        "excess": -25.49
      },
      {
        "year": 2017,
        "portfolio": -3.31,
        "spy": 14.34,
        "excess": -17.64
      },
      {
        "year": 2018,
        "portfolio": 0.64,
        "spy": 11.2,
        "excess": -10.55
      },
      {
        "year": 2019,
        "portfolio": 8.64,
        "spy": 7.43,
        "excess": 1.21
      },
      {
        "year": 2020,
        "portfolio": 55.1,
        "spy": 40.98,
        "excess": 14.12
      },
      {
        "year": 2021,
        "portfolio": -17.0,
        "spy": -10.68,
        "excess": -6.32
      },
      {
        "year": 2022,
        "portfolio": 13.14,
        "spy": 18.08,
        "excess": -4.95
      },
      {
        "year": 2023,
        "portfolio": -1.52,
        "spy": 25.44,
        "excess": -26.96
      },
      {
        "year": 2024,
        "portfolio": -7.09,
        "spy": 14.42,
        "excess": -21.51
      }
    ]
  },
  "SET": {
    "universe": "SET",
    "n_periods": 25,
    "years": 25.0,
    "frequency": "annual",
    "cash_periods": 4,
    "invested_periods": 21,
    "avg_stocks_when_invested": 24.1,
    "portfolio": {
      "total_return": 122.54,
      "cagr": 3.25,
      "max_drawdown": -35.63,
      "annualized_volatility": 15.8,
      "sharpe_ratio": 0.048,
      "sortino_ratio": 0.085,
      "calmar_ratio": 0.091,
      "var_95": -21.91,
      "max_consecutive_losses": 4,
      "pct_negative_periods": 36.0
    },
    "spy": {
      "total_return": 561.67,
      "cagr": 7.85,
      "max_drawdown": -38.01,
      "annualized_volatility": 16.63,
      "sharpe_ratio": 0.322,
      "sortino_ratio": 0.561,
      "calmar_ratio": 0.207,
      "var_95": -22.45,
      "max_consecutive_losses": 2,
      "pct_negative_periods": 20.0
    },
    "comparison": {
      "excess_cagr": -4.6,
      "win_rate": 48.0,
      "information_ratio": -0.306,
      "tracking_error": 15.66,
      "up_capture": 46.13,
      "down_capture": 42.16,
      "beta": 0.508,
      "alpha": -1.97
    },
    "excess_cagr": -4.6,
    "win_rate_vs_spy": 48.0,
    "annual_returns": [
      {
        "year": 2000,
        "portfolio": 0.0,
        "spy": -14.78,
        "excess": 14.78
      },
      {
        "year": 2001,
        "portfolio": 0.0,
        "spy": -22.45,
        "excess": 22.45
      },
      {
        "year": 2002,
        "portfolio": 0.0,
        "spy": 6.86,
        "excess": -6.86
      },
      {
        "year": 2003,
        "portfolio": 0.0,
        "spy": 14.93,
        "excess": -14.93
      },
      {
        "year": 2004,
        "portfolio": 1.01,
        "spy": 8.87,
        "excess": -7.86
      },
      {
        "year": 2005,
        "portfolio": -3.24,
        "spy": 7.99,
        "excess": -11.22
      },
      {
        "year": 2006,
        "portfolio": 25.32,
        "spy": 20.95,
        "excess": 4.38
      },
      {
        "year": 2007,
        "portfolio": -12.73,
        "spy": -15.2,
        "excess": 2.46
      },
      {
        "year": 2008,
        "portfolio": -21.91,
        "spy": -26.9,
        "excess": 4.99
      },
      {
        "year": 2009,
        "portfolio": 24.51,
        "spy": 15.98,
        "excess": 8.53
      },
      {
        "year": 2010,
        "portfolio": 43.92,
        "spy": 33.55,
        "excess": 10.37
      },
      {
        "year": 2011,
        "portfolio": 23.21,
        "spy": 4.19,
        "excess": 19.02
      },
      {
        "year": 2012,
        "portfolio": 15.61,
        "spy": 20.74,
        "excess": -5.13
      },
      {
        "year": 2013,
        "portfolio": 8.07,
        "spy": 24.74,
        "excess": -16.67
      },
      {
        "year": 2014,
        "portfolio": 7.42,
        "spy": 7.18,
        "excess": 0.24
      },
      {
        "year": 2015,
        "portfolio": 5.31,
        "spy": 2.71,
        "excess": 2.59
      },
      {
        "year": 2016,
        "portfolio": 0.6,
        "spy": 18.58,
        "excess": -17.98
      },
      {
        "year": 2017,
        "portfolio": -0.66,
        "spy": 14.34,
        "excess": -15.0
      },
      {
        "year": 2018,
        "portfolio": 17.89,
        "spy": 11.2,
        "excess": 6.69
      },
      {
        "year": 2019,
        "portfolio": -9.96,
        "spy": 7.43,
        "excess": -17.4
      },
      {
        "year": 2020,
        "portfolio": 25.11,
        "spy": 40.98,
        "excess": -15.87
      },
      {
        "year": 2021,
        "portfolio": -3.3,
        "spy": -10.68,
        "excess": 7.38
      },
      {
        "year": 2022,
        "portfolio": -2.71,
        "spy": 18.08,
        "excess": -20.8
      },
      {
        "year": 2023,
        "portfolio": -11.58,
        "spy": 25.44,
        "excess": -37.02
      },
      {
        "year": 2024,
        "portfolio": -22.6,
        "spy": 14.42,
        "excess": -37.02
      }
    ]
  },
  "SHZ_SHH": {
    "universe": "China",
    "n_periods": 25,
    "years": 25.0,
    "frequency": "annual",
    "cash_periods": 0,
    "invested_periods": 25,
    "avg_stocks_when_invested": 20.3,
    "portfolio": {
      "total_return": 227.67,
      "cagr": 4.86,
      "max_drawdown": -63.64,
      "annualized_volatility": 34.24,
      "sharpe_ratio": 0.069,
      "sortino_ratio": 0.166,
      "calmar_ratio": 0.076,
      "var_95": -26.94,
      "max_consecutive_losses": 4,
      "pct_negative_periods": 44.0
    },
    "spy": {
      "total_return": 82.25,
      "cagr": 2.43,
      "max_drawdown": -52.53,
      "annualized_volatility": 36.64,
      "sharpe_ratio": -0.002,
      "sortino_ratio": -0.005,
      "calmar_ratio": 0.046,
      "var_95": -27.33,
      "max_consecutive_losses": 4,
      "pct_negative_periods": 52.0
    },
    "comparison": {
      "excess_cagr": 2.43,
      "win_rate": 52.0,
      "information_ratio": 0.164,
      "tracking_error": 13.06,
      "up_capture": 105.16,
      "down_capture": 83.24,
      "beta": 0.873,
      "alpha": 2.42
    },
    "excess_cagr": 2.43,
    "win_rate_vs_spy": 52.0,
    "annual_returns": [
      {
        "year": 2000,
        "portfolio": 6.27,
        "spy": 16.37,
        "excess": -10.1
      },
      {
        "year": 2001,
        "portfolio": -26.91,
        "spy": -21.81,
        "excess": -5.1
      },
      {
        "year": 2002,
        "portfolio": -21.41,
        "spy": -13.06,
        "excess": -8.35
      },
      {
        "year": 2003,
        "portfolio": -12.83,
        "spy": -3.9,
        "excess": -8.93
      },
      {
        "year": 2004,
        "portfolio": -27.39,
        "spy": -27.33,
        "excess": -0.06
      },
      {
        "year": 2005,
        "portfolio": 44.28,
        "spy": 62.07,
        "excess": -17.79
      },
      {
        "year": 2006,
        "portfolio": 109.63,
        "spy": 126.03,
        "excess": -16.4
      },
      {
        "year": 2007,
        "portfolio": -22.99,
        "spy": -30.88,
        "excess": 7.89
      },
      {
        "year": 2008,
        "portfolio": 36.66,
        "spy": 15.41,
        "excess": 21.26
      },
      {
        "year": 2009,
        "portfolio": -1.84,
        "spy": -22.13,
        "excess": 20.3
      },
      {
        "year": 2010,
        "portfolio": 31.1,
        "spy": 18.04,
        "excess": 13.05
      },
      {
        "year": 2011,
        "portfolio": -14.85,
        "spy": -20.86,
        "excess": 6.01
      },
      {
        "year": 2012,
        "portfolio": -4.47,
        "spy": -9.86,
        "excess": 5.39
      },
      {
        "year": 2013,
        "portfolio": 22.44,
        "spy": 2.63,
        "excess": 19.81
      },
      {
        "year": 2014,
        "portfolio": 91.36,
        "spy": 89.99,
        "excess": 1.36
      },
      {
        "year": 2015,
        "portfolio": 2.56,
        "spy": -23.62,
        "excess": 26.18
      },
      {
        "year": 2016,
        "portfolio": 4.28,
        "spy": 6.94,
        "excess": -2.65
      },
      {
        "year": 2017,
        "portfolio": -22.1,
        "spy": -13.15,
        "excess": -8.95
      },
      {
        "year": 2018,
        "portfolio": 5.38,
        "spy": 9.67,
        "excess": -4.29
      },
      {
        "year": 2019,
        "portfolio": 19.0,
        "spy": 1.53,
        "excess": 17.47
      },
      {
        "year": 2020,
        "portfolio": 8.19,
        "spy": 13.85,
        "excess": -5.67
      },
      {
        "year": 2021,
        "portfolio": -0.7,
        "spy": -3.22,
        "excess": 2.52
      },
      {
        "year": 2022,
        "portfolio": 11.56,
        "spy": -4.74,
        "excess": 16.3
      },
      {
        "year": 2023,
        "portfolio": -26.94,
        "spy": -7.61,
        "excess": -19.32
      },
      {
        "year": 2024,
        "portfolio": 18.73,
        "spy": 15.27,
        "excess": 3.45
      }
    ]
  },
  "SIX": {
    "universe": "SIX",
    "n_periods": 25,
    "years": 25.0,
    "frequency": "annual",
    "cash_periods": 0,
    "invested_periods": 25,
    "avg_stocks_when_invested": 18.1,
    "portfolio": {
      "total_return": 392.09,
      "cagr": 6.58,
      "max_drawdown": -36.88,
      "annualized_volatility": 15.72,
      "sharpe_ratio": 0.387,
      "sortino_ratio": 0.775,
      "calmar_ratio": 0.178,
      "var_95": -14.92,
      "max_consecutive_losses": 2,
      "pct_negative_periods": 28.0
    },
    "spy": {
      "total_return": 561.67,
      "cagr": 7.85,
      "max_drawdown": -38.01,
      "annualized_volatility": 16.63,
      "sharpe_ratio": 0.442,
      "sortino_ratio": 0.847,
      "calmar_ratio": 0.207,
      "var_95": -22.45,
      "max_consecutive_losses": 2,
      "pct_negative_periods": 20.0
    },
    "comparison": {
      "excess_cagr": -1.27,
      "win_rate": 48.0,
      "information_ratio": -0.113,
      "tracking_error": 12.55,
      "up_capture": 74.95,
      "down_capture": 50.72,
      "beta": 0.662,
      "alpha": 1.21
    },
    "excess_cagr": -1.27,
    "win_rate_vs_spy": 48.0,
    "annual_returns": [
      {
        "year": 2000,
        "portfolio": 21.4,
        "spy": -14.78,
        "excess": 36.18
      },
      {
        "year": 2001,
        "portfolio": -11.65,
        "spy": -22.45,
        "excess": 10.8
      },
      {
        "year": 2002,
        "portfolio": -11.6,
        "spy": 6.86,
        "excess": -18.46
      },
      {
        "year": 2003,
        "portfolio": 17.05,
        "spy": 14.93,
        "excess": 2.12
      },
      {
        "year": 2004,
        "portfolio": 15.32,
        "spy": 8.87,
        "excess": 6.46
      },
      {
        "year": 2005,
        "portfolio": 14.53,
        "spy": 7.99,
        "excess": 6.54
      },
      {
        "year": 2006,
        "portfolio": 34.83,
        "spy": 20.95,
        "excess": 13.89
      },
      {
        "year": 2007,
        "portfolio": -13.21,
        "spy": -15.2,
        "excess": 1.99
      },
      {
        "year": 2008,
        "portfolio": -27.28,
        "spy": -26.9,
        "excess": -0.38
      },
      {
        "year": 2009,
        "portfolio": 26.19,
        "spy": 15.98,
        "excess": 10.21
      },
      {
        "year": 2010,
        "portfolio": 17.18,
        "spy": 33.55,
        "excess": -16.37
      },
      {
        "year": 2011,
        "portfolio": 2.21,
        "spy": 4.19,
        "excess": -1.98
      },
      {
        "year": 2012,
        "portfolio": 26.16,
        "spy": 20.74,
        "excess": 5.42
      },
      {
        "year": 2013,
        "portfolio": 16.5,
        "spy": 24.74,
        "excess": -8.25
      },
      {
        "year": 2014,
        "portfolio": 8.99,
        "spy": 7.18,
        "excess": 1.81
      },
      {
        "year": 2015,
        "portfolio": 6.13,
        "spy": 2.71,
        "excess": 3.42
      },
      {
        "year": 2016,
        "portfolio": 20.49,
        "spy": 18.58,
        "excess": 1.91
      },
      {
        "year": 2017,
        "portfolio": 8.08,
        "spy": 14.34,
        "excess": -6.26
      },
      {
        "year": 2018,
        "portfolio": -6.27,
        "spy": 11.2,
        "excess": -17.47
      },
      {
        "year": 2019,
        "portfolio": 2.6,
        "spy": 7.43,
        "excess": -4.83
      },
      {
        "year": 2020,
        "portfolio": 30.66,
        "spy": 40.98,
        "excess": -10.33
      },
      {
        "year": 2021,
        "portfolio": -14.92,
        "spy": -10.68,
        "excess": -4.24
      },
      {
        "year": 2022,
        "portfolio": -1.1,
        "spy": 18.08,
        "excess": -19.18
      },
      {
        "year": 2023,
        "portfolio": 8.41,
        "spy": 25.44,
        "excess": -17.03
      },
      {
        "year": 2024,
        "portfolio": 2.86,
        "spy": 14.42,
        "excess": -11.56
      }
    ]
  },
  "STO": {
    "universe": "STO",
    "n_periods": 25,
    "years": 25.0,
    "frequency": "annual",
    "cash_periods": 7,
    "invested_periods": 18,
    "avg_stocks_when_invested": 22.6,
    "portfolio": {
      "total_return": 363.86,
      "cagr": 6.33,
      "max_drawdown": -35.69,
      "annualized_volatility": 16.63,
      "sharpe_ratio": 0.26,
      "sortino_ratio": 0.532,
      "calmar_ratio": 0.177,
      "var_95": -18.69,
      "max_consecutive_losses": 2,
      "pct_negative_periods": 16.0
    },
    "spy": {
      "total_return": 561.67,
      "cagr": 7.85,
      "max_drawdown": -38.01,
      "annualized_volatility": 16.63,
      "sharpe_ratio": 0.352,
      "sortino_ratio": 0.628,
      "calmar_ratio": 0.207,
      "var_95": -22.45,
      "max_consecutive_losses": 2,
      "pct_negative_periods": 20.0
    },
    "comparison": {
      "excess_cagr": -1.52,
      "win_rate": 44.0,
      "information_ratio": -0.139,
      "tracking_error": 11.46,
      "up_capture": 77.31,
      "down_capture": 63.63,
      "beta": 0.763,
      "alpha": -0.14
    },
    "excess_cagr": -1.52,
    "win_rate_vs_spy": 44.0,
    "annual_returns": [
      {
        "year": 2000,
        "portfolio": 0.0,
        "spy": -14.78,
        "excess": 14.78
      },
      {
        "year": 2001,
        "portfolio": 0.0,
        "spy": -22.45,
        "excess": 22.45
      },
      {
        "year": 2002,
        "portfolio": 0.0,
        "spy": 6.86,
        "excess": -6.86
      },
      {
        "year": 2003,
        "portfolio": 0.0,
        "spy": 14.93,
        "excess": -14.93
      },
      {
        "year": 2004,
        "portfolio": 0.0,
        "spy": 8.87,
        "excess": -8.87
      },
      {
        "year": 2005,
        "portfolio": 14.76,
        "spy": 7.99,
        "excess": 6.78
      },
      {
        "year": 2006,
        "portfolio": 0.0,
        "spy": 20.95,
        "excess": -20.95
      },
      {
        "year": 2007,
        "portfolio": -28.38,
        "spy": -15.2,
        "excess": -13.18
      },
      {
        "year": 2008,
        "portfolio": -10.21,
        "spy": -26.9,
        "excess": 16.69
      },
      {
        "year": 2009,
        "portfolio": 0.0,
        "spy": 15.98,
        "excess": -15.98
      },
      {
        "year": 2010,
        "portfolio": 27.37,
        "spy": 33.55,
        "excess": -6.18
      },
      {
        "year": 2011,
        "portfolio": -9.27,
        "spy": 4.19,
        "excess": -13.45
      },
      {
        "year": 2012,
        "portfolio": 16.13,
        "spy": 20.74,
        "excess": -4.61
      },
      {
        "year": 2013,
        "portfolio": 27.56,
        "spy": 24.74,
        "excess": 2.82
      },
      {
        "year": 2014,
        "portfolio": 15.99,
        "spy": 7.18,
        "excess": 8.82
      },
      {
        "year": 2015,
        "portfolio": 5.7,
        "spy": 2.71,
        "excess": 2.98
      },
      {
        "year": 2016,
        "portfolio": 37.08,
        "spy": 18.58,
        "excess": 18.49
      },
      {
        "year": 2017,
        "portfolio": 10.23,
        "spy": 14.34,
        "excess": -4.11
      },
      {
        "year": 2018,
        "portfolio": 11.38,
        "spy": 11.2,
        "excess": 0.18
      },
      {
        "year": 2019,
        "portfolio": 0.33,
        "spy": 7.43,
        "excess": -7.1
      },
      {
        "year": 2020,
        "portfolio": 45.03,
        "spy": 40.98,
        "excess": 4.05
      },
      {
        "year": 2021,
        "portfolio": -18.69,
        "spy": -10.68,
        "excess": -8.01
      },
      {
        "year": 2022,
        "portfolio": 19.39,
        "spy": 18.08,
        "excess": 1.3
      },
      {
        "year": 2023,
        "portfolio": 20.62,
        "spy": 25.44,
        "excess": -4.82
      },
      {
        "year": 2024,
        "portfolio": 4.44,
        "spy": 14.42,
        "excess": -9.98
      }
    ]
  },
  "TAI": {
    "universe": "Taiwan",
    "n_periods": 25,
    "years": 25.0,
    "frequency": "annual",
    "cash_periods": 8,
    "invested_periods": 17,
    "avg_stocks_when_invested": 28.8,
    "portfolio": {
      "total_return": 291.89,
      "cagr": 5.62,
      "max_drawdown": -10.94,
      "annualized_volatility": 11.51,
      "sharpe_ratio": 0.401,
      "sortino_ratio": 1.211,
      "calmar_ratio": 0.513,
      "var_95": -9.72,
      "max_consecutive_losses": 1,
      "pct_negative_periods": 20.0
    },
    "spy": {
      "total_return": 172.09,
      "cagr": 4.09,
      "max_drawdown": -41.11,
      "annualized_volatility": 19.22,
      "sharpe_ratio": 0.161,
      "sortino_ratio": 0.28,
      "calmar_ratio": 0.099,
      "var_95": -19.72,
      "max_consecutive_losses": 2,
      "pct_negative_periods": 32.0
    },
    "comparison": {
      "excess_cagr": 1.53,
      "win_rate": 48.0,
      "information_ratio": 0.023,
      "tracking_error": 14.58,
      "up_capture": 71.42,
      "down_capture": 27.64,
      "beta": 0.392,
      "alpha": 3.41
    },
    "excess_cagr": 1.53,
    "win_rate_vs_spy": 48.0,
    "annual_returns": [
      {
        "year": 2000,
        "portfolio": 0.0,
        "spy": -41.11,
        "excess": 41.11
      },
      {
        "year": 2001,
        "portfolio": 0.0,
        "spy": 2.21,
        "excess": -2.21
      },
      {
        "year": 2002,
        "portfolio": 0.0,
        "spy": 2.01,
        "excess": -2.01
      },
      {
        "year": 2003,
        "portfolio": 0.0,
        "spy": 12.79,
        "excess": -12.79
      },
      {
        "year": 2004,
        "portfolio": 0.0,
        "spy": 9.13,
        "excess": -9.13
      },
      {
        "year": 2005,
        "portfolio": 0.0,
        "spy": 7.13,
        "excess": -7.13
      },
      {
        "year": 2006,
        "portfolio": 0.0,
        "spy": 33.06,
        "excess": -33.06
      },
      {
        "year": 2007,
        "portfolio": 0.0,
        "spy": -17.74,
        "excess": 17.74
      },
      {
        "year": 2008,
        "portfolio": -6.02,
        "spy": -9.33,
        "excess": 3.32
      },
      {
        "year": 2009,
        "portfolio": 18.65,
        "spy": 9.95,
        "excess": 8.7
      },
      {
        "year": 2010,
        "portfolio": 29.6,
        "spy": 19.7,
        "excess": 9.9
      },
      {
        "year": 2011,
        "portfolio": -10.94,
        "spy": -16.29,
        "excess": 5.35
      },
      {
        "year": 2012,
        "portfolio": 8.38,
        "spy": 9.13,
        "excess": -0.75
      },
      {
        "year": 2013,
        "portfolio": 17.93,
        "spy": 18.33,
        "excess": -0.4
      },
      {
        "year": 2014,
        "portfolio": -1.0,
        "spy": -1.11,
        "excess": 0.11
      },
      {
        "year": 2015,
        "portfolio": 1.72,
        "spy": -6.6,
        "excess": 8.32
      },
      {
        "year": 2016,
        "portfolio": 16.86,
        "spy": 18.86,
        "excess": -1.99
      },
      {
        "year": 2017,
        "portfolio": 4.84,
        "spy": 3.51,
        "excess": 1.33
      },
      {
        "year": 2018,
        "portfolio": 9.3,
        "spy": 0.81,
        "excess": 8.49
      },
      {
        "year": 2019,
        "portfolio": 12.43,
        "spy": 8.65,
        "excess": 3.78
      },
      {
        "year": 2020,
        "portfolio": 17.42,
        "spy": 50.02,
        "excess": -32.6
      },
      {
        "year": 2021,
        "portfolio": -5.68,
        "spy": -19.72,
        "excess": 14.05
      },
      {
        "year": 2022,
        "portfolio": 19.08,
        "spy": 20.17,
        "excess": -1.09
      },
      {
        "year": 2023,
        "portfolio": 31.97,
        "spy": 35.64,
        "excess": -3.66
      },
      {
        "year": 2024,
        "portfolio": -9.72,
        "spy": -2.57,
        "excess": -7.16
      }
    ]
  },
  "TSX": {
    "universe": "Canada",
    "n_periods": 25,
    "years": 25.0,
    "frequency": "annual",
    "cash_periods": 2,
    "invested_periods": 23,
    "avg_stocks_when_invested": 24.8,
    "portfolio": {
      "total_return": 522.16,
      "cagr": 7.59,
      "max_drawdown": -31.45,
      "annualized_volatility": 16.19,
      "sharpe_ratio": 0.314,
      "sortino_ratio": 0.615,
      "calmar_ratio": 0.241,
      "var_95": -11.83,
      "max_consecutive_losses": 2,
      "pct_negative_periods": 28.0
    },
    "spy": {
      "total_return": 163.55,
      "cagr": 3.95,
      "max_drawdown": -31.44,
      "annualized_volatility": 14.63,
      "sharpe_ratio": 0.099,
      "sortino_ratio": 0.157,
      "calmar_ratio": 0.126,
      "var_95": -24.12,
      "max_consecutive_losses": 3,
      "pct_negative_periods": 40.0
    },
    "comparison": {
      "excess_cagr": 3.63,
      "win_rate": 60.0,
      "information_ratio": 0.35,
      "tracking_error": 10.93,
      "up_capture": 124.9,
      "down_capture": 53.08,
      "beta": 0.833,
      "alpha": 3.88
    },
    "excess_cagr": 3.63,
    "win_rate_vs_spy": 60.0,
    "annual_returns": [
      {
        "year": 2000,
        "portfolio": 0.0,
        "spy": -24.12,
        "excess": 24.12
      },
      {
        "year": 2001,
        "portfolio": 19.35,
        "spy": -9.35,
        "excess": 28.7
      },
      {
        "year": 2002,
        "portfolio": -11.83,
        "spy": -0.33,
        "excess": -11.5
      },
      {
        "year": 2003,
        "portfolio": 0.0,
        "spy": 21.42,
        "excess": -21.42
      },
      {
        "year": 2004,
        "portfolio": 29.24,
        "spy": 17.14,
        "excess": 12.1
      },
      {
        "year": 2005,
        "portfolio": 23.56,
        "spy": 18.02,
        "excess": 5.54
      },
      {
        "year": 2006,
        "portfolio": 24.46,
        "spy": 19.87,
        "excess": 4.59
      },
      {
        "year": 2007,
        "portfolio": 0.46,
        "spy": -0.22,
        "excess": 0.68
      },
      {
        "year": 2008,
        "portfolio": -31.45,
        "spy": -26.99,
        "excess": -4.46
      },
      {
        "year": 2009,
        "portfolio": 26.32,
        "spy": 9.27,
        "excess": 17.05
      },
      {
        "year": 2010,
        "portfolio": 38.46,
        "spy": 19.56,
        "excess": 18.89
      },
      {
        "year": 2011,
        "portfolio": -1.03,
        "spy": -11.49,
        "excess": 10.46
      },
      {
        "year": 2012,
        "portfolio": 9.28,
        "spy": 2.78,
        "excess": 6.5
      },
      {
        "year": 2013,
        "portfolio": 24.12,
        "spy": 24.89,
        "excess": -0.78
      },
      {
        "year": 2014,
        "portfolio": -6.99,
        "spy": -3.76,
        "excess": -3.23
      },
      {
        "year": 2015,
        "portfolio": -0.25,
        "spy": -2.59,
        "excess": 2.34
      },
      {
        "year": 2016,
        "portfolio": 13.06,
        "spy": 6.11,
        "excess": 6.95
      },
      {
        "year": 2017,
        "portfolio": 6.97,
        "spy": 7.49,
        "excess": -0.52
      },
      {
        "year": 2018,
        "portfolio": 10.01,
        "spy": 1.28,
        "excess": 8.73
      },
      {
        "year": 2019,
        "portfolio": -9.28,
        "spy": -5.15,
        "excess": -4.13
      },
      {
        "year": 2020,
        "portfolio": 32.06,
        "spy": 29.47,
        "excess": 2.59
      },
      {
        "year": 2021,
        "portfolio": -6.71,
        "spy": -5.92,
        "excess": -0.79
      },
      {
        "year": 2022,
        "portfolio": 6.16,
        "spy": 6.18,
        "excess": -0.02
      },
      {
        "year": 2023,
        "portfolio": 9.05,
        "spy": 8.66,
        "excess": 0.4
      },
      {
        "year": 2024,
        "portfolio": 15.2,
        "spy": 22.39,
        "excess": -7.19
      }
    ]
  },
  "XETRA": {
    "universe": "XETRA",
    "n_periods": 25,
    "years": 25.0,
    "frequency": "annual",
    "cash_periods": 0,
    "invested_periods": 25,
    "avg_stocks_when_invested": 20.6,
    "portfolio": {
      "total_return": 370.74,
      "cagr": 6.39,
      "max_drawdown": -46.64,
      "annualized_volatility": 16.31,
      "sharpe_ratio": 0.269,
      "sortino_ratio": 0.497,
      "calmar_ratio": 0.137,
      "var_95": -23.48,
      "max_consecutive_losses": 3,
      "pct_negative_periods": 24.0
    },
    "spy": {
      "total_return": 241.86,
      "cagr": 5.04,
      "max_drawdown": -53.43,
      "annualized_volatility": 21.11,
      "sharpe_ratio": 0.144,
      "sortino_ratio": 0.239,
      "calmar_ratio": 0.094,
      "var_95": -25.17,
      "max_consecutive_losses": 3,
      "pct_negative_periods": 36.0
    },
    "comparison": {
      "excess_cagr": 1.35,
      "win_rate": 52.0,
      "information_ratio": 0.025,
      "tracking_error": 17.48,
      "up_capture": 62.88,
      "down_capture": 13.66,
      "beta": 0.455,
      "alpha": 3.01
    },
    "excess_cagr": 1.35,
    "win_rate_vs_spy": 52.0,
    "annual_returns": [
      {
        "year": 2000,
        "portfolio": 37.94,
        "spy": -12.21,
        "excess": 50.15
      },
      {
        "year": 2001,
        "portfolio": -23.48,
        "spy": -31.32,
        "excess": 7.84
      },
      {
        "year": 2002,
        "portfolio": -12.99,
        "spy": -22.76,
        "excess": 9.77
      },
      {
        "year": 2003,
        "portfolio": -5.31,
        "spy": 23.38,
        "excess": -28.69
      },
      {
        "year": 2004,
        "portfolio": 0.7,
        "spy": 15.62,
        "excess": -14.92
      },
      {
        "year": 2005,
        "portfolio": 12.65,
        "spy": 23.56,
        "excess": -10.91
      },
      {
        "year": 2006,
        "portfolio": 14.96,
        "spy": 39.31,
        "excess": -24.35
      },
      {
        "year": 2007,
        "portfolio": -23.82,
        "spy": -20.77,
        "excess": -3.06
      },
      {
        "year": 2008,
        "portfolio": -14.79,
        "spy": -25.17,
        "excess": 10.38
      },
      {
        "year": 2009,
        "portfolio": 34.99,
        "spy": 23.64,
        "excess": 11.35
      },
      {
        "year": 2010,
        "portfolio": 27.09,
        "spy": 27.58,
        "excess": -0.49
      },
      {
        "year": 2011,
        "portfolio": 7.81,
        "spy": -12.72,
        "excess": 20.54
      },
      {
        "year": 2012,
        "portfolio": 11.33,
        "spy": 21.78,
        "excess": -10.45
      },
      {
        "year": 2013,
        "portfolio": 15.36,
        "spy": 25.29,
        "excess": -9.93
      },
      {
        "year": 2014,
        "portfolio": 16.32,
        "spy": 11.99,
        "excess": 4.34
      },
      {
        "year": 2015,
        "portfolio": 6.22,
        "spy": -12.53,
        "excess": 18.75
      },
      {
        "year": 2016,
        "portfolio": 6.61,
        "spy": 28.49,
        "excess": -21.88
      },
      {
        "year": 2017,
        "portfolio": 8.07,
        "spy": -1.9,
        "excess": 9.97
      },
      {
        "year": 2018,
        "portfolio": 1.6,
        "spy": 2.36,
        "excess": -0.76
      },
      {
        "year": 2019,
        "portfolio": 8.99,
        "spy": 0.65,
        "excess": 8.33
      },
      {
        "year": 2020,
        "portfolio": 32.67,
        "spy": 24.12,
        "excess": 8.54
      },
      {
        "year": 2021,
        "portfolio": -6.51,
        "spy": -18.38,
        "excess": 11.87
      },
      {
        "year": 2022,
        "portfolio": 4.52,
        "spy": 25.89,
        "excess": -21.37
      },
      {
        "year": 2023,
        "portfolio": 18.34,
        "spy": 14.26,
        "excess": 4.08
      },
      {
        "year": 2024,
        "portfolio": 11.32,
        "spy": 29.47,
        "excess": -18.15
      }
    ]
  }
}