{
  "universe": "Taiwan",
  "n_periods": 103,
  "years": 25.8,
  "frequency": "quarterly",
  "cash_periods": 25,
  "invested_periods": 78,
  "avg_stocks_when_invested": 28.0,
  "portfolio": {
    "total_return": 149.99,
    "cagr": 3.62,
    "max_drawdown": -54.2,
    "annualized_volatility": 19.67,
    "sharpe_ratio": 0.133,
    "sortino_ratio": 0.208,
    "calmar_ratio": 0.067,
    "var_95": -15.61,
    "max_consecutive_losses": 5,
    "pct_negative_periods": 30.1
  },
  "spy": {
    "total_return": 627.45,
    "cagr": 8.01,
    "max_drawdown": -45.53,
    "annualized_volatility": 16.97,
    "sharpe_ratio": 0.413,
    "sortino_ratio": 0.622,
    "calmar_ratio": 0.176,
    "var_95": -15.01,
    "max_consecutive_losses": 6,
    "pct_negative_periods": 31.07
  },
  "comparison": {
    "excess_cagr": -4.39,
    "win_rate": 45.63,
    "information_ratio": -0.237,
    "tracking_error": 15.88,
    "up_capture": 65.28,
    "down_capture": 71.01,
    "beta": 0.734,
    "alpha": -2.52
  },
  "excess_cagr": -4.39,
  "win_rate_vs_spy": 45.63,
  "annual_returns": [
    {
      "year": 2000,
      "portfolio": 0.0,
      "spy": -10.5,
      "excess": 10.5
    },
    {
      "year": 2001,
      "portfolio": 0.0,
      "spy": -9.17,
      "excess": 9.17
    },
    {
      "year": 2002,
      "portfolio": 0.0,
      "spy": -19.92,
      "excess": 19.92
    },
    {
      "year": 2003,
      "portfolio": 0.0,
      "spy": 24.12,
      "excess": -24.12
    },
    {
      "year": 2004,
      "portfolio": 0.0,
      "spy": 10.24,
      "excess": -10.24
    },
    {
      "year": 2005,
      "portfolio": 0.0,
      "spy": 7.17,
      "excess": -7.17
    },
    {
      "year": 2006,
      "portfolio": 17.42,
      "spy": 13.65,
      "excess": 3.78
    },
    {
      "year": 2007,
      "portfolio": 8.68,
      "spy": 4.4,
      "excess": 4.27
    },
    {
      "year": 2008,
      "portfolio": -46.93,
      "spy": -34.31,
      "excess": -12.62
    },
    {
      "year": 2009,
      "portfolio": 113.13,
      "spy": 24.73,
      "excess": 88.4
    },
    {
      "year": 2010,
      "portfolio": 9.16,
      "spy": 14.31,
      "excess": -5.14
    },
    {
      "year": 2011,
      "portfolio": -24.74,
      "spy": 2.46,
      "excess": -27.2
    },
    {
      "year": 2012,
      "portfolio": 18.81,
      "spy": 17.09,
      "excess": 1.72
    },
    {
      "year": 2013,
      "portfolio": 11.21,
      "spy": 27.77,
      "excess": -16.57
    },
    {
      "year": 2014,
      "portfolio": 12.9,
      "spy": 14.5,
      "excess": -1.59
    },
    {
      "year": 2015,
      "portfolio": -24.86,
      "spy": -0.12,
      "excess": -24.73
    },
    {
      "year": 2016,
      "portfolio": 9.05,
      "spy": 14.45,
      "excess": -5.4
    },
    {
      "year": 2017,
      "portfolio": 22.87,
      "spy": 21.64,
      "excess": 1.23
    },
    {
      "year": 2018,
      "portfolio": -14.62,
      "spy": -5.15,
      "excess": -9.47
    },
    {
      "year": 2019,
      "portfolio": 25.45,
      "spy": 32.31,
      "excess": -6.86
    },
    {
      "year": 2020,
      "portfolio": 41.46,
      "spy": 15.64,
      "excess": 25.83
    },
    {
      "year": 2021,
      "portfolio": 4.91,
      "spy": 31.26,
      "excess": -26.35
    },
    {
      "year": 2022,
      "portfolio": -21.71,
      "spy": -18.99,
      "excess": -2.72
    },
    {
      "year": 2023,
      "portfolio": 25.26,
      "spy": 26.0,
      "excess": -0.74
    },
    {
      "year": 2024,
      "portfolio": -7.58,
      "spy": 25.28,
      "excess": -32.86
    },
    {
      "year": 2025,
      "portfolio": -2.58,
      "spy": 15.34,
      "excess": -17.92
    }
  ]
}